{
	"articles": {
		"id": 0,
		"access": 0,
		"revision": 1760985155205
	},
	"camp": {
		"id": 0,
		"access": 0,
		"revision": 1760985155208
	},
	"camping": {
		"id": 0,
		"access": 0,
		"revision": 1760985155267
	},
	"carousel": {
		"id": 0,
		"access": 0,
		"revision": 1760985155271
	},
	"chords": {
		"id": 0,
		"access": 0,
		"revision": 1760991183953
	},
	"home": {
		"id": 0,
		"access": 0,
		"revision": 1760988224405
	},
	"iching": {
		"id": 0,
		"access": 0,
		"revision": 1760985155406
	},
	"index": {
		"id": 0,
		"access": 0,
		"revision": 1760985155409
	},
	"songbook": {
		"id": 0,
		"access": 0,
		"revision": 1760988224373
	},
	"test-cookies": {
		"id": 0,
		"access": 0,
		"revision": 1760985155421
	},
	"test-file-api": {
		"id": 0,
		"access": 0,
		"revision": 1760985155424
	},
	"test-iching": {
		"id": 0,
		"access": 0,
		"revision": 1716593322739
	},
	"test-load-data": {
		"id": 0,
		"access": 0,
		"revision": 1760985155426
	},
	"test-lyrics": {
		"id": 0,
		"access": 0,
		"revision": 1760988224367
	},
	"test-post-api": {
		"id": 0,
		"access": 0,
		"revision": 1760985155430
	},
	"test-redwords": {
		"id": 0,
		"access": 0,
		"revision": 1760985155432
	},
	"test-svg": {
		"id": 0,
		"access": 0,
		"revision": 1760985155435
	},
	"test-types": {
		"id": 0,
		"access": 0,
		"revision": 1760985155439
	},
	"test-yaml": {
		"id": 0,
		"access": 0,
		"revision": 1760985155443
	},
	"threads": {
		"id": 0,
		"access": 0,
		"revision": 1760985155445
	},
	"timeline": {
		"id": 0,
		"access": 0,
		"revision": 1760985155462
	}
}